cythoninstallhelpers/__init__.py
cythoninstallhelpers/_version.py
cythoninstallhelpers/build_config.py
cythoninstallhelpers/configure_logger.py
cythoninstallhelpers/get_version.py
cythoninstallhelpers/make_cython_extensions.py
cythoninstallhelpers/tests/__init__.py
cythoninstallhelpers/tests/_version.py
cythoninstallhelpers/tests/_version2.py
cythoninstallhelpers/tests/_version_broken.py
cythoninstallhelpers/tests/module_with_logging.py
cythoninstallhelpers/tests/test_logger.py
cythoninstallhelpers/tests/test_makeext.py
cythoninstallhelpers/tests/test_version.py
cythoninstallhelpers/tests/examplepackage/__init__.py
cythoninstallhelpers/tests/examplepackage/example_cython.pxd
cythoninstallhelpers/tests/examplepackage/example_cython.pyx
cythoninstallhelpers/tests/examplepackage/example_cython.pyxbld
cythoninstallhelpers-1.3.0.dist-info/METADATA
cythoninstallhelpers-1.3.0.dist-info/WHEEL
cythoninstallhelpers-1.3.0.dist-info/top_level.txt
cythoninstallhelpers-1.3.0.dist-info/RECORD
